flypipe/__init__.py
flypipe/config.py
flypipe/config_test.py
flypipe/conftest.py
flypipe/exceptions.py
flypipe/node.py
flypipe/node_dependencies_mixin.py
flypipe/node_function.py
flypipe/node_function_test.py
flypipe/node_graph.py
flypipe/node_graph_test.py
flypipe/node_result.py
flypipe/node_run_context.py
flypipe/node_test.py
flypipe/node_type.py
flypipe/output_column_set.py
flypipe/pyspark_node_test.py
flypipe/run_context.py
flypipe/run_context_test.py
flypipe/run_status.py
flypipe/runner.py
flypipe/runner_test.py
flypipe/template.py
flypipe/utils.py
flypipe/utils_test.py
flypipe/version.txt
flypipe/cache/__init__.py
flypipe/cache/cache.py
flypipe/cache/cache_context.py
flypipe/cache/cache_context_test.py
flypipe/cache/cache_mode.py
flypipe/cache/cache_test.py
flypipe/catalog/__init__.py
flypipe/catalog/catalog.py
flypipe/catalog/catalog_test.py
flypipe/catalog/group.py
flypipe/catalog/group_test.py
flypipe/catalog/node.py
flypipe/catalog/node_test.py
flypipe/converter/__init__.py
flypipe/converter/dataframe.py
flypipe/converter/dataframe_test.py
flypipe/dataframe/__init__.py
flypipe/dataframe/dataframe_wrapper.py
flypipe/dataframe/dataframe_wrapper_test.py
flypipe/dataframe/pandas_dataframe_wrapper.py
flypipe/dataframe/pandas_dataframe_wrapper_test.py
flypipe/dataframe/pandas_on_spark_dataframe_wrapper.py
flypipe/dataframe/pandas_on_spark_dataframe_wrapper_test.py
flypipe/dataframe/spark_dataframe_wrapper.py
flypipe/dataframe/spark_dataframe_wrapper_test.py
flypipe/datasource/__init__.py
flypipe/datasource/spark.py
flypipe/datasource/spark_test.py
flypipe/dependency/__init__.py
flypipe/dependency/node_input.py
flypipe/dependency/node_input_preprocess_func_test.py
flypipe/dependency/node_input_test.py
flypipe/dependency/preprocess.py
flypipe/dependency/preprocess_mode.py
flypipe/examples/__init__.py
flypipe/examples/pipeline/__init__.py
flypipe/examples/pipeline/dwh/__init__.py
flypipe/examples/pipeline/dwh/raw/__init__.py
flypipe-5.0.0.dist-info/licenses/LICENSE
flypipe-5.0.0.dist-info/WHEEL
flypipe-5.0.0.dist-info/METADATA
flypipe-5.0.0.dist-info/RECORD
