Metadata-Version: 2.4
Name: flypipe
Version: 5.0.0
Summary: Flypipe
Author-email: Jose Helio de Brum Muller <josemuller.flypipe@gmail.com>, Chris Marwick <chrismarwick.flypipe@gmail.com>
Requires-Python: >=3.8
Classifier: Development Status :: 5 - Production/Stable
Classifier: Intended Audience :: Developers
Classifier: Intended Audience :: Information Technology
Classifier: License :: OSI Approved :: Apache Software License
Classifier: Programming Language :: Python :: 3
License-File: LICENSE
Requires-Dist: Jinja2 >=3.1
Requires-Dist: networkx >=3.1
Requires-Dist: tabulate >=0.9
Requires-Dist: sparkleframe >=0.2
Project-URL: Home, https://github.com/flypipe/flypipe.git
